taggit_anywhere/__init__.py
taggit_anywhere/admin.py
taggit_anywhere/apps.py
taggit_anywhere/models.py
django_taggit_anywhere-1.0.0.dist-info/LICENSE
django_taggit_anywhere-1.0.0.dist-info/METADATA
django_taggit_anywhere-1.0.0.dist-info/WHEEL
django_taggit_anywhere-1.0.0.dist-info/top_level.txt
django_taggit_anywhere-1.0.0.dist-info/RECORD
